README.md
setup.cfg
setup.py
grafos/__init__.py
grafos/basic.py
grafos/edges.py
grafos/features.py
grafos/file.py
grafos/matrix.py
grafos/search.py
grafos.egg-info/PKG-INFO
grafos.egg-info/SOURCES.txt
grafos.egg-info/dependency_links.txt
grafos.egg-info/not-zip-safe
grafos.egg-info/requires.txt
grafos.egg-info/top_level.txt
memoize/__init__.py