Metadata-Version: 1.1
Name: grafos
Version: 1.0.1
Summary: Ferramenta de algoritmos de Teoria e Modelagem de Grafos
Home-page: http://github.com/gfviegas/grafos
Author: Gustavo Viegas, Lucas Duarte
Author-email: gustavo.viegas@ufv.br, lucas.duarte@ufv.br
License: Apache
Download-URL: https://github.com/gfviegas/grafos/archive/1.0.tar.gz
Platform: UNKNOWN
